collate_sqlfluff-3.3.6.dist-info/licenses/LICENSE.md
sqlfluff/__init__.py
sqlfluff/__main__.py
sqlfluff/diff_quality_plugin.py
sqlfluff/py.typed
sqlfluff/api/__init__.py
sqlfluff/api/info.py
sqlfluff/api/simple.py
sqlfluff/cli/__init__.py
sqlfluff/cli/autocomplete.py
sqlfluff/cli/commands.py
sqlfluff/cli/formatters.py
sqlfluff/cli/helpers.py
sqlfluff/cli/outputstream.py
sqlfluff/core/__init__.py
sqlfluff/core/default_config.cfg
sqlfluff/core/errors.py
sqlfluff/core/formatter.py
sqlfluff/core/timing.py
sqlfluff/core/types.py
sqlfluff/core/config/__init__.py
sqlfluff/core/config/file.py
sqlfluff/core/config/fluffconfig.py
sqlfluff/core/config/ini.py
sqlfluff/core/config/loader.py
sqlfluff/core/config/removed.py
sqlfluff/core/config/toml.py
sqlfluff/core/config/validate.py
sqlfluff/core/dialects/__init__.py
sqlfluff/core/dialects/base.py
sqlfluff/core/dialects/common.py
sqlfluff/core/helpers/__init__.py
sqlfluff/core/helpers/dict.py
sqlfluff/core/helpers/file.py
sqlfluff/core/helpers/slice.py
sqlfluff/core/helpers/string.py
sqlfluff/core/linter/__init__.py
sqlfluff/core/linter/common.py
sqlfluff/core/linter/discovery.py
sqlfluff/core/linter/fix.py
sqlfluff/core/linter/linted_dir.py
sqlfluff/core/linter/linted_file.py
sqlfluff/core/linter/linter.py
sqlfluff/core/linter/linting_result.py
sqlfluff/core/linter/patch.py
sqlfluff/core/linter/runner.py
sqlfluff/core/parser/__init__.py
sqlfluff/core/parser/context.py
sqlfluff/core/parser/helpers.py
sqlfluff/core/parser/lexer.py
sqlfluff/core/parser/markers.py
sqlfluff/core/parser/match_algorithms.py
sqlfluff/core/parser/match_result.py
sqlfluff/core/parser/matchable.py
sqlfluff/core/parser/parser.py
sqlfluff/core/parser/parsers.py
sqlfluff/core/parser/types.py
sqlfluff/core/parser/grammar/__init__.py
sqlfluff/core/parser/grammar/anyof.py
sqlfluff/core/parser/grammar/base.py
sqlfluff/core/parser/grammar/conditional.py
sqlfluff/core/parser/grammar/delimited.py
sqlfluff/core/parser/grammar/noncode.py
sqlfluff/core/parser/grammar/sequence.py
collate_sqlfluff-3.3.6.dist-info/METADATA
collate_sqlfluff-3.3.6.dist-info/WHEEL
collate_sqlfluff-3.3.6.dist-info/entry_points.txt
collate_sqlfluff-3.3.6.dist-info/top_level.txt
collate_sqlfluff-3.3.6.dist-info/RECORD
